hangarbay/__init__.py
hangarbay/address.py
hangarbay/api.py
hangarbay/cli.py
hangarbay/config.py
hangarbay/schemas.py
hangarbay-0.5.0.dist-info/licenses/LICENSE
pipelines/__init__.py
pipelines/fetch.py
pipelines/normalize.py
pipelines/publish.py
hangarbay-0.5.0.dist-info/METADATA
hangarbay-0.5.0.dist-info/WHEEL
hangarbay-0.5.0.dist-info/entry_points.txt
hangarbay-0.5.0.dist-info/top_level.txt
hangarbay-0.5.0.dist-info/RECORD
